wordle/__init__.py
wordle/wordle.py
wordle/data/dictionary.json
pywordle_cli-0.1.3.dist-info/LICENSE
pywordle_cli-0.1.3.dist-info/METADATA
pywordle_cli-0.1.3.dist-info/WHEEL
pywordle_cli-0.1.3.dist-info/entry_points.txt
pywordle_cli-0.1.3.dist-info/top_level.txt
pywordle_cli-0.1.3.dist-info/RECORD
