Metadata-Version: 2.1
Name: pywordle-cli
Version: 0.1.3
Summary: A command line based wordle game
Author: Ousmane Barry
Author-email: abarr156@uottawa.ca
Classifier: Development Status :: 4 - Beta
Classifier: Environment :: Console
Classifier: Intended Audience :: End Users/Desktop
Classifier: Programming Language :: Python :: 3
Classifier: Programming Language :: Python :: 3.7
Classifier: Programming Language :: Python :: 3.8
Classifier: Programming Language :: Python :: 3.9
Classifier: Programming Language :: Python :: 3.10
Classifier: License :: OSI Approved :: MIT License
Classifier: Operating System :: OS Independent
Classifier: Topic :: Games/Entertainment :: Puzzle Games
Requires-Python: >=3.7
License-File: LICENSE
Requires-Dist: colorama
Requires-Dist: setuptools
